niugdelt/__init__.py
niugdelt/niugdelt0.py
niugdelt/niugdelt1.py
niugdelt/setup.py
niugdelt-0.0.1.dist-info/METADATA
niugdelt-0.0.1.dist-info/WHEEL
niugdelt-0.0.1.dist-info/licenses/LICENSE.txt
niugdelt-0.0.1.dist-info/RECORD
